lionrender/__init__.py
lionrender/renderpass.py
lionrender/version.py
panda3d_lion_render-0.1.0.dist-info/LICENSE
panda3d_lion_render-0.1.0.dist-info/METADATA
panda3d_lion_render-0.1.0.dist-info/WHEEL
panda3d_lion_render-0.1.0.dist-info/top_level.txt
panda3d_lion_render-0.1.0.dist-info/RECORD
