Metadata-Version: 2.1
Name: panda3d-lion-render
Version: 0.1.0
Summary: A rendering toolkit for Panda3D
Home-page: https://github.com/kupoman/panda3d-lion-render
Author: Daniel Stokes
License: MIT
Keywords: panda3d
Platform: UNKNOWN
Classifier: Development Status :: 4 - Beta
Classifier: License :: OSI Approved :: MIT License
Classifier: Programming Language :: Python
Classifier: Programming Language :: Python :: 3
Requires-Dist: panda3d
